pycalc3/__init__.py
pycalc3/calculator.py
pycalc3-0.0.3.dist-info/LICENSE
pycalc3-0.0.3.dist-info/WHEEL
pycalc3-0.0.3.dist-info/METADATA
pycalc3-0.0.3.dist-info/RECORD
