Metadata-Version: 2.1
Name: pycalc3
Version: 0.0.3
Summary: Basic math operations with internal memory.
Author-email: Simas Sirutavicius <sirutavicius.simas@gmail.com>
Requires-Python: >=3.6
Classifier: License :: OSI Approved :: MIT License
Classifier: Programming Language :: Python :: 3
Project-URL: Source, https://github.com/simsiru/py-calculator
